<?xml version="1.0" encoding="UTF-8"?>
<ti:work xml:lang="lat" xmlns:ti="http://chs.harvard.edu/xmlns/cts" groupUrn="urn:cts:latinLit:phi0474" projid="latinLit:phi031" urn="urn:cts:latinLit:phi0474.phi031">
    <ti:title xml:lang="lat">Pro Milone</ti:title>
    
    <ti:edition urn="urn:cts:latinLit:phi0474.phi031.perseus-lat1" workUrn="urn:cts:latinLit:phi0474.phi031" xml:lang="lat">
        <ti:label xml:lang="lat">Pro Milone</ti:label>
        <ti:description xml:lang="mul">Cicero. M. Tulli Ciceronis. Orationes, Vol. 4. Clark, Albert Curtis, editor. Oxford: Clarendon Press, 1909.</ti:description>
        <ti:memberof collection="Perseus:collection:Greco-Roman" />
    </ti:edition>
</ti:work>
