<work xmlns="http://chs.harvard.edu/xmlns/cts" groupUrn="urn:cts:latinLit:phi0914" projid="latinLit:phi001" urn="urn:cts:latinLit:phi0914.phi001" xml:lang="lat">
    <title xml:lang="lat">Ab urbe condita</title>
    <translation projid="latinLit:perseus-eng3" urn="urn:cts:latinLit:phi0914.phi001.perseus-eng3" workUrn="urn:cts:latinLit:phi0914.phi001" xml:lang="eng">
        <label xml:lang="eng">The History of Rome</label>
        <description xml:lang="eng">Livy. History of Rome, Volumes 1-2. Roberts, Canon, Rev, translator. 
            London, New York: J. M. Dent &amp; Sons; E. P. Dutton and Co., 1912.</description>
        <memberof collection="Perseus:collection:Greco-Roman" />
    </translation>
    <edition urn="urn:cts:latinLit:phi0914.phi001.perseus-lat2" workUrn="urn:cts:latinLit:phi0914.phi001">
        <label xml:lang="lat">Ab urbe condita</label>
        <description xml:lang="lat">Titi Livi ab urbe condita libri editionem priman, Pars I-IV, Libri I-XL. Editio Stereotypica. 
            Weissenborn, Wilhelm; Mueller, Moritz, editors. Leipzig: Teubner, 1884-1911.</description>
        <memberof collection="Perseus:collection:Greco-Roman" />
    </edition>   
</work>
